stytch/__init__.py
stytch/py.typed
stytch/version.py
stytch/b2b/__init__.py
stytch/b2b/client.py
stytch/b2b/api/__init__.py
stytch/b2b/api/discovery.py
stytch/b2b/api/discovery_intermediate_sessions.py
stytch/b2b/api/discovery_organizations.py
stytch/b2b/api/idp.py
stytch/b2b/api/idp_oauth.py
stytch/b2b/api/impersonation.py
stytch/b2b/api/magic_links.py
stytch/b2b/api/magic_links_discovery.py
stytch/b2b/api/magic_links_email.py
stytch/b2b/api/magic_links_email_discovery.py
stytch/b2b/api/oauth.py
stytch/b2b/api/oauth_discovery.py
stytch/b2b/api/organizations.py
stytch/b2b/api/organizations_members.py
stytch/b2b/api/organizations_members_connected_apps.py
stytch/b2b/api/organizations_members_oauth_providers.py
stytch/b2b/api/otp.py
stytch/b2b/api/otp_email.py
stytch/b2b/api/otp_email_discovery.py
stytch/b2b/api/otp_sms.py
stytch/b2b/api/passwords.py
stytch/b2b/api/passwords_discovery.py
stytch/b2b/api/passwords_discovery_email.py
stytch/b2b/api/passwords_email.py
stytch/b2b/api/passwords_existing_password.py
stytch/b2b/api/passwords_session.py
stytch/b2b/api/rbac.py
stytch/b2b/api/rbac_organizations.py
stytch/b2b/api/recovery_codes.py
stytch/b2b/api/scim.py
stytch/b2b/api/scim_connection.py
stytch/b2b/api/sessions.py
stytch/b2b/api/sso.py
stytch/b2b/api/sso_external.py
stytch/b2b/api/sso_oidc.py
stytch/b2b/api/sso_saml.py
stytch/b2b/api/totps.py
stytch/b2b/models/__init__.py
stytch/b2b/models/discovery.py
stytch/b2b/models/discovery_intermediate_sessions.py
stytch/b2b/models/discovery_organizations.py
stytch/b2b/models/idp.py
stytch/b2b/models/idp_oauth.py
stytch/b2b/models/impersonation.py
stytch/b2b/models/magic_links.py
stytch/b2b/models/magic_links_discovery.py
stytch/b2b/models/magic_links_email.py
stytch/b2b/models/magic_links_email_discovery.py
stytch/b2b/models/mfa.py
stytch/b2b/models/oauth.py
stytch/b2b/models/oauth_discovery.py
stytch/b2b/models/organizations.py
stytch/b2b/models/organizations_members.py
stytch-14.2.0.dist-info/licenses/LICENSE.txt
stytch-14.2.0.dist-info/METADATA
stytch-14.2.0.dist-info/WHEEL
stytch-14.2.0.dist-info/top_level.txt
stytch-14.2.0.dist-info/RECORD
