Metadata-Version: 2.4
Name: stytch
Version: 14.2.0
Summary: Stytch python client
Download-URL: https://github.com/stytchauth/stytch-python
Author: Stytch
Author-email: hello@stytch.com
License: MIT
Keywords: stytch,user,authentication
Classifier: License :: OSI Approved :: MIT License
Classifier: Intended Audience :: Developers
Classifier: Programming Language :: Python :: 3
Classifier: Programming Language :: Python :: 3 :: Only
Classifier: Programming Language :: Python :: 3.8
Classifier: Programming Language :: Python :: 3.9
Classifier: Programming Language :: Python :: 3.10
Classifier: Programming Language :: Python :: 3.11
Requires-Python: >=3.8
License-File: LICENSE.txt
Requires-Dist: aiohttp>=3.8.3
Requires-Dist: requests>=2.7.0
Requires-Dist: pydantic>=1.10.2
Requires-Dist: pyjwt[crypto]>=2.9.0
Dynamic: author
Dynamic: author-email
Dynamic: classifier
Dynamic: description
Dynamic: description-content-type
Dynamic: download-url
Dynamic: keywords
Dynamic: license
Dynamic: license-file
Dynamic: requires-dist
Dynamic: requires-python
Dynamic: summary
